pypiapijson/__init__.py
pypiapijson/asyncs.py
pypiapijson/testfile.py
pypiapijson-2.3.dist-info/METADATA
pypiapijson-2.3.dist-info/WHEEL
pypiapijson-2.3.dist-info/top_level.txt
pypiapijson-2.3.dist-info/RECORD
