Metadata-Version: 2.1
Name: pypiapijson
Version: 2.3
Summary: A client for connect to pypi.org api to retrieve the python packages!
Home-page: https://github.com/dumb-stuff/pypiapijson
Author: Rukchad Wongprayoon
Author-email: mooping3roblox@gmail.com
License: MIT
Project-URL: Documentation, https://pypiapijson.biomooping.tk
Keywords: Tools
Platform: UNKNOWN
Requires-Dist: aiohttp
